AUTHORS.rst
CHANGELOG.rst
LICENSE
MANIFEST.in
README.rst
setup.py
jmbo_show.egg-info/PKG-INFO
jmbo_show.egg-info/SOURCES.txt
jmbo_show.egg-info/dependency_links.txt
jmbo_show.egg-info/not-zip-safe
jmbo_show.egg-info/requires.txt
jmbo_show.egg-info/top_level.txt
show/__init__.py
show/admin.py
show/models.py
show/tests.py
show/urls.py
show/utils.py
show/views.py
show/migrations/0001_initial.py
show/migrations/0001_initial.pyc
show/migrations/0002_auto__add_field_show_start_time.py
show/migrations/0002_auto__add_field_show_start_time.pyc
show/migrations/__init__.py
show/migrations/__init__.pyc
show/templates/basic/show/current_radio.html
show/templates/basic/show/schedule.html
show/templates/basic/show/show_detail.html
show/templates/basic/show/inclusion_tags/contributor_detail.html
show/templates/basic/show/inclusion_tags/radioshow_detail.html
show/templates/basic/show/inclusion_tags/radioshow_list_item_ipod.html
show/templates/basic/show/inclusion_tags/show_detail.html
show/templates/basic/show/inclusion_tags/show_list_item_ipod.html
show/templatetags/__init__.py
show/templatetags/__init__.pyc
show/templatetags/show_tags.py
show/templatetags/show_tags.pyc
show/view_modifiers/__init__.py
show/view_modifiers/__init__.pyc
show/view_modifiers/items.py
show/view_modifiers/items.pyc